wakanda_whisper/__init__.py
wakanda_whisper/base.py
wakanda_whisper/languages.py
wakanda_whisper/version.py
wakanda_whisper-0.1.1.dist-info/licenses/LICENSE
wakanda_whisper-0.1.1.dist-info/METADATA
wakanda_whisper-0.1.1.dist-info/WHEEL
wakanda_whisper-0.1.1.dist-info/top_level.txt
wakanda_whisper-0.1.1.dist-info/RECORD
