Metadata-Version: 2.4
Name: wakanda-whisper
Version: 0.1.1
Summary: A framework for automatic speech recognition (ASR) for african languages using OpenAI Whisper
Author-email: Lawrence Francis <lawrencedikeu@gmail.com>
Maintainer-email: Lawrence Francis <lawrencedikeu@gmail.com>
License-Expression: MIT
Project-URL: Homepage, https://github.com/wakandaai/wakanda-whisper
Project-URL: Issues, https://github.com/wakandaai/wakanda-whisper/issues
Classifier: Programming Language :: Python :: 3
Classifier: Operating System :: OS Independent
Requires-Python: >=3.9
License-File: LICENSE
Requires-Dist: openai-whisper
Requires-Dist: huggingface_hub
Requires-Dist: pyyaml
Dynamic: license-file
